{
  "name": "Usdog TCH",
  "timestamp": "2024-01-05T11:25:09Z",
  "version": {
    "major": 2,
    "minor": 11,
    "patch": 0
  },
  "tags": {},
  "logoURI": "https://shadowswap.xyz/logo.png",
  "keywords": ["usdog", "extended"],
  "tokens": [
   {
            "name": "USDOG Token",
            "symbol": "USDOG",
            "address": "0x08Bc55Ac7B63f4D808D3172D20eD66d6FFeb45e0",
            "chainId": 7,
            "decimals": 18,
            "logoURI": "https://pub-89889c1f7aea4fc08378f41c30a7fa44.r2.dev/usdog-2.svg"
    }
    
  ]
}
